{
  "title": "Publishing and subscribing to MQTT Topics from a Micronaut Application",
  "intro": "Learn how to use Mosquitto as an MQTT broker, create a Micronaut CLI application and publish an MQTT topic, and subscribe to the MQTT topic in a different Micronaut Messaging application.",
  "authors": ["Sergio del Amo"],
  "tags": ["messaging"],
  "categories": ["Messaging"],
  "publicationDate": "2022-03-14",
  "apps": [
    {
      "applicationType": "MESSAGING",
      "name": "app",
      "features": ["yaml", "mqtt"],
      "javaFeatures": [ "graalvm", "awaitility"],
      "kotlinFeatures": [ "graalvm", "awaitility"]
    },
    {
      "applicationType": "CLI",
      "name": "cli",
      "features": ["yaml", "mqtt"],
      "javaFeatures": [ "graalvm", "awaitility"],
      "kotlinFeatures": [ "graalvm", "awaitility", "kapt"]
    }
  ]
}
